apiverve_passwordstrength/__init__.py
apiverve_passwordstrength/apiClient.py
apiverve_passwordstrength/exceptions.py
apiverve_passwordstrength/setup.py
apiverve_passwordstrength/setup_dep.py
apiverve_passwordstrength/tests/__init__.py
apiverve_passwordstrength/tests/test_api.py
apiverve_passwordstrength-1.1.5.dist-info/LICENSE
apiverve_passwordstrength-1.1.5.dist-info/METADATA
apiverve_passwordstrength-1.1.5.dist-info/WHEEL
apiverve_passwordstrength-1.1.5.dist-info/top_level.txt
apiverve_passwordstrength-1.1.5.dist-info/RECORD
